wordpress/__init__.py
wordpress/wordpress.py
wordpress/wordpress_old.py
Wordpress-1.2.dist-info/LICENSE
Wordpress-1.2.dist-info/METADATA
Wordpress-1.2.dist-info/WHEEL
Wordpress-1.2.dist-info/top_level.txt
Wordpress-1.2.dist-info/RECORD
