Metadata-Version: 2.1
Name: Wordpress
Version: 1.2
Summary: A Python library for interacting with the WordPress REST API
Author-email: Ankush Kumar <ankush1611996@gmail.com>
Project-URL: Homepage, https://github.com/AnkushRozra/wordpress
Project-URL: Bug Tracker, https://github.com/AnkushRozra/wordpress/issues
Keywords: WordPress,WordPress API,WordPress SDK,REST API,wp python,WP
Classifier: Programming Language :: Python :: 3
Classifier: License :: OSI Approved :: MIT License
Classifier: Operating System :: OS Independent
Requires-Python: >=3.8
License-File: LICENSE
Requires-Dist: requests
